mkwcs/__init__.py
mkwcs/lib.py
mkwcs-0.1.data/scripts/get_angle
mkwcs-0.1.data/scripts/mkwcs_with_angle
mkwcs-0.1.data/scripts/mkwcs_with_angle_range
mkwcs-0.1.dist-info/METADATA
mkwcs-0.1.dist-info/WHEEL
mkwcs-0.1.dist-info/top_level.txt
mkwcs-0.1.dist-info/RECORD
