Metadata-Version: 2.1
Name: mkwcs
Version: 0.1
Summary: script that makes a WCS solution for a regular image (N up, E left) with some additional rotation.
Home-page: https://github.com/carlos-contreras-velasquez/mkwcs
Author: Carlos Contreras Velasquez
Author-email: carlos.contreras.velasquez@gmail.com
License: Free to use for everyone.
Platform: UNKNOWN
Requires-Dist: astropy
Requires-Dist: astroquery
Requires-Dist: matplotlib
Requires-Dist: photutils
Requires-Dist: numpy
